bjarkan/__init__.py
bjarkan/client.py
bjarkan/config.py
bjarkan/exceptions.py
bjarkan/models.py
bjarkan/core/__init__.py
bjarkan/core/base.py
bjarkan/core/executor.py
bjarkan/core/orderbook.py
bjarkan/core/trades.py
bjarkan/utils/__init__.py
bjarkan/utils/helpers.py
bjarkan/utils/logger.py
bjarkan_sdk-9.0.2.dist-info/LICENSE
bjarkan_sdk-9.0.2.dist-info/METADATA
bjarkan_sdk-9.0.2.dist-info/WHEEL
bjarkan_sdk-9.0.2.dist-info/top_level.txt
bjarkan_sdk-9.0.2.dist-info/RECORD
