Metadata-Version: 2.2
Name: bjarkan-sdk
Version: 9.0.2
Summary: SDK for Bjarkan cryptocurrency trading system
Author-email: Manuel de Cara <manu.de.cara@gmail.com>
License: MIT
Classifier: Development Status :: 3 - Alpha
Classifier: Intended Audience :: Developers
Classifier: License :: OSI Approved :: MIT License
Classifier: Operating System :: OS Independent
Classifier: Programming Language :: Python :: 3
Classifier: Programming Language :: Python :: 3.9
Requires-Python: >=3.9
License-File: LICENSE
Requires-Dist: ccxt>=4.1.13
Requires-Dist: pydantic>=2.5.2
Requires-Dist: loguru>=0.7.2
Requires-Dist: python-dotenv>=1.0.0
Requires-Dist: logtail-python>=0.2.5
Provides-Extra: dev
Requires-Dist: build; extra == "dev"
Requires-Dist: twine; extra == "dev"
Requires-Dist: black; extra == "dev"
Requires-Dist: isort; extra == "dev"
Requires-Dist: mypy; extra == "dev"
Requires-Dist: pytest; extra == "dev"
Requires-Dist: pytest-asyncio; extra == "dev"
Requires-Dist: pytest-cov; extra == "dev"
